{"title":"HDI Rank (hdi 2022) \/ Property Rights (efi 2022)","xaxis":"HDI Rank (hdi 2022)","yaxis":"Property Rights (efi 2022)","minx":"1","maxx":"189","miny":"0.2","maxy":"100.0","data":[{"c":"Albania","w":"69","h":"55.5"},{"c":"Algeria","w":"91","h":"27.9"},{"c":"Angola","w":"148","h":"39.8"},{"c":"Argentina","w":"46","h":"35.1"},{"c":"Armenia","w":"81","h":"50.4"},{"c":"Australia","w":"8","h":"91.7"},{"c":"Austria","w":"18","h":"98.4"},{"c":"Azerbaijan","w":"88","h":"53.6"},{"c":"Bahamas","w":"58","h":"61.1"},{"c":"Bahrain","w":"42","h":"65.9"},{"c":"Bangladesh","w":"133","h":"36.3"},{"c":"Barbados","w":"58","h":"72.6"},{"c":"Belarus","w":"53","h":"34.5"},{"c":"Belgium","w":"14","h":"92.5"},{"c":"Belize","w":"110","h":"34.7"},{"c":"Benin","w":"158","h":"44.3"},{"c":"Bhutan","w":"129","h":"67.2"},{"c":"Bolivia","w":"107","h":"14.1"},{"c":"Botswana","w":"100","h":"74.2"},{"c":"Brazil","w":"84","h":"50.3"},{"c":"Bulgaria","w":"56","h":"77.3"},{"c":"Myanmar","w":"147","h":"23.1"},{"c":"Burundi","w":"185","h":"18.8"},{"c":"Cambodia","w":"144","h":"41.2"},{"c":"Cameroon","w":"153","h":"39.1"},{"c":"Canada","w":"16","h":"89.5"},{"c":"Chad","w":"187","h":"28.9"},{"c":"Chile","w":"43","h":"73.0"},{"c":"China","w":"85","h":"43.7"},{"c":"Colombia","w":"83","h":"50.9"},{"c":"Comoros","w":"156","h":"28.9"},{"c":"Croatia","w":"43","h":"81.1"},{"c":"Cuba","w":"70","h":"31.5"},{"c":"Cyprus","w":"33","h":"85.6"},{"c":"Denmark","w":"10","h":"98.6"},{"c":"Djibouti","w":"166","h":"33.1"},{"c":"Dominica","w":"94","h":"68.1"},{"c":"Ecuador","w":"86","h":"31.4"},{"c":"Egypt","w":"116","h":"39.0"},{"c":"Eritrea","w":"180","h":"8.6"},{"c":"Estonia","w":"29","h":"91.5"},{"c":"Eswatini","w":"138","h":"46.1"},{"c":"Ethiopia","w":"173","h":"38.1"},{"c":"Fiji","w":"93","h":"53.2"},{"c":"Finland","w":"11","h":"100.0"},{"c":"France","w":"26","h":"93.8"},{"c":"Gabon","w":"119","h":"26.8"},{"c":"Gambia","w":"172","h":"47.6"},{"c":"Georgia","w":"61","h":"63.8"},{"c":"Germany","w":"6","h":"95.7"},{"c":"Ghana","w":"138","h":"60.7"},{"c":"Greece","w":"32","h":"76.0"},{"c":"Guatemala","w":"127","h":"39.8"},{"c":"Guinea","w":"178","h":"21.4"},{"c":"Guinea-Bissau","w":"175","h":"29.1"},{"c":"Guyana","w":"122","h":"46.9"},{"c":"Haiti","w":"170","h":"24.1"},{"c":"Honduras","w":"132","h":"40.3"},{"c":"Hungary","w":"40","h":"75.8"},{"c":"Iceland","w":"4","h":"97.1"},{"c":"India","w":"131","h":"49.9"},{"c":"Indonesia","w":"107","h":"38.6"},{"c":"Iran","w":"70","h":"26.6"},{"c":"Ireland","w":"2","h":"92.6"},{"c":"Israel","w":"19","h":"83.2"},{"c":"Italy","w":"29","h":"81.7"},{"c":"Jamaica","w":"101","h":"65.0"},{"c":"Japan","w":"19","h":"94.6"},{"c":"Jordan","w":"102","h":"53.7"},{"c":"Kazakhstan","w":"51","h":"55.3"},{"c":"Kenya","w":"143","h":"40.6"},{"c":"Kiribati","w":"134","h":"70.6"},{"c":"Kuwait","w":"64","h":"41.9"},{"c":"Kyrgyzstan","w":"120","h":"25.1"},{"c":"Latvia","w":"37","h":"88.5"},{"c":"Lebanon","w":"92","h":"33.7"},{"c":"Lesotho","w":"165","h":"45.0"},{"c":"Liberia","w":"175","h":"32.2"},{"c":"Lithuania","w":"34","h":"88.6"},{"c":"Luxembourg","w":"23","h":"97.4"},{"c":"Madagascar","w":"164","h":"40.3"},{"c":"Malawi","w":"174","h":"48.1"},{"c":"Malaysia","w":"62","h":"65.6"},{"c":"Maldives","w":"95","h":"47.2"},{"c":"Mali","w":"184","h":"34.0"},{"c":"Malta","w":"28","h":"87.8"},{"c":"Mauritania","w":"157","h":"36.9"},{"c":"Mauritius","w":"66","h":"85.6"},{"c":"Mexico","w":"74","h":"47.7"},{"c":"Micronesia","w":"136","h":"54.3"},{"c":"Moldova","w":"90","h":"55.9"},{"c":"Mongolia","w":"99","h":"48.8"},{"c":"Montenegro","w":"48","h":"61.3"},{"c":"Morocco","w":"121","h":"57.8"},{"c":"Mozambique","w":"181","h":"31.9"},{"c":"Namibia","w":"130","h":"63.8"},{"c":"Nepal","w":"142","h":"37.4"},{"c":"Netherlands","w":"8","h":"96.2"},{"c":"Nicaragua","w":"128","h":"30.1"},{"c":"Niger","w":"189","h":"37.4"},{"c":"Nigeria","w":"161","h":"22.1"},{"c":"Norway","w":"1","h":"99.6"},{"c":"Oman","w":"60","h":"74.9"},{"c":"Pakistan","w":"154","h":"29.0"},{"c":"Panama","w":"57","h":"58.8"},{"c":"Paraguay","w":"103","h":"45.5"},{"c":"Peru","w":"79","h":"49.7"},{"c":"Philippines","w":"107","h":"47.1"},{"c":"Poland","w":"35","h":"72.3"},{"c":"Portugal","w":"38","h":"89.9"},{"c":"Qatar","w":"45","h":"68.6"},{"c":"Romania","w":"49","h":"81.0"},{"c":"Russia","w":"52","h":"36.8"},{"c":"Rwanda","w":"160","h":"61.1"},{"c":"Samoa","w":"111","h":"78.4"},{"c":"Senegal","w":"168","h":"58.0"},{"c":"Serbia","w":"64","h":"58.8"},{"c":"Seychelles","w":"67","h":"78.8"},{"c":"Singapore","w":"11","h":"94.4"},{"c":"Slovakia","w":"39","h":"83.2"},{"c":"Slovenia","w":"22","h":"89.7"},{"c":"Spain","w":"25","h":"87.7"},{"c":"Sudan","w":"170","h":"22.2"},{"c":"Suriname","w":"97","h":"51.2"},{"c":"Sweden","w":"7","h":"97.3"},{"c":"Switzerland","w":"2","h":"95.2"},{"c":"Tajikistan","w":"125","h":"29.5"},{"c":"Tanzania","w":"163","h":"36.9"},{"c":"Thailand","w":"79","h":"44.2"},{"c":"Timor-Leste","w":"141","h":"30.8"},{"c":"Togo","w":"167","h":"36.8"},{"c":"Tonga","w":"104","h":"64.2"},{"c":"Tunisia","w":"95","h":"60.9"},{"c":"Turkey","w":"54","h":"42.0"},{"c":"Turkmenistan","w":"111","h":"19.0"},{"c":"Uganda","w":"159","h":"48.3"},{"c":"Ukraine","w":"74","h":"39.7"},{"c":"Uruguay","w":"55","h":"84.0"},{"c":"Uzbekistan","w":"106","h":"31.6"},{"c":"Vanuatu","w":"140","h":"57.8"},{"c":"Venezuela","w":"113","h":"0.2"},{"c":"Vietnam","w":"117","h":"49.6"},{"c":"Zambia","w":"146","h":"38.3"},{"c":"Zimbabwe","w":"150","h":"20.8"}]}